paperless_asn_labels/__init__.py
paperless_asn_labels/main.py
paperless_asn_labels/sheet.py
paperless_asn_labels-1.0.1.dist-info/LICENSE
paperless_asn_labels-1.0.1.dist-info/METADATA
paperless_asn_labels-1.0.1.dist-info/WHEEL
paperless_asn_labels-1.0.1.dist-info/entry_points.txt
paperless_asn_labels-1.0.1.dist-info/RECORD
