Metadata-Version: 2.1
Name: paperless-asn-labels
Version: 1.0.1
Summary: Creates archive serial number (ASN) label sheets
Author: Adrian Figueroa
Author-email: elagil@takanome.de
Requires-Python: >=3.10,<4.0
Classifier: Programming Language :: Python :: 3
Classifier: Programming Language :: Python :: 3.10
Classifier: Programming Language :: Python :: 3.11
Classifier: Programming Language :: Python :: 3.12
Classifier: Programming Language :: Python :: 3.13
Requires-Dist: click (>=8.1.7,<9.0.0)
Requires-Dist: fpdf2 (>=2.7.8,<3.0.0)
Requires-Dist: segno (>=1.6.1,<2.0.0)
